{
    "$schema": "http://schema.management.azure.com/schemas/2015-01-01/deploymentTemplate.json#",
    "contentVersion": "1.0.0.0",
  "parameters": {
    "loadbalancerName": {
      "type": "string",
      "minLength": 1
    },
    "vnetName": {
      "type": "string",
      "minLength": 1
    },
    "vnetRG": {
      "type": "string",
      "minLength": 1
    },
    "availabilitySetName": {
      "type": "string",
    },
    "vmName": {
      "type": "string",
    },
    "subnetRef": {
      "type": "string",
    },
    "dnsNameforPublicIP": {
      "type": "string",
    },
	"pipName": {
      "type": "string",
      "minLength": 1,
      "maxLength": 80
    },
    "environment": {
      "type": "string",
      "allowedValues": [
        "Production",
        "Staging",
        "Test",
        "Development",
        "Q/A",
        "Bastion",
        "Other"
      ],
    },
    "buildDate": {
      "type": "string",
    },
    "buildBy": {
      "type": "string",
    }
  },
  "variables": {
    "vnetId": "[resourceId(parameters('vnetRG'),'Microsoft.Network/virtualnetworks',parameters('vnetName'))]"
  },
    "resources": [
	 {
      "apiVersion": "2015-05-01-preview",
      "type": "Microsoft.Network/publicIPAddresses",
      "name": "[parameters('pipName')]",
      "location": "[resourceGroup().location]",
      "properties": {
        "publicIPAllocationMethod": "Dynamic",
        "dnsSettings": {
          "domainNameLabel": "[parameters('dnsNameforPublicIP')]"
        }
      }
    },
        {
            "apiVersion": "2015-06-15",
            "name": "[parameters('loadbalancerName')]",
            "type": "Microsoft.Network/loadBalancers",
            "location": "[resourceGroup().location]",
            "dependsOn": [
			    "[concat('Microsoft.Network/publicIPAddresses/', parameters('pipName'))]"
			],
            "properties": {
                "frontendIPConfigurations": [
                    {
                        "name": "loadBalancerFrontEnd",
                        "properties": {
                          "subnet": {
                            "id": "[resourceId('Microsoft.Network/publicIPAddresses', parameters('pipName'))]"
                          }
                        }
                    }
                ],
                "backendAddressPools": [
                    {
                        "name": "loadBalancerBackEnd"
                    }
                ],
                "loadBalancingRules": [
                    {
                        "properties": {
                            "frontendIPConfiguration": {
                                "id": "[concat(resourceId('Microsoft.Network/loadBalancers', parameters('loadbalancerName')), '/frontendIpConfigurations/loadBalancerFrontEnd')]"
                            },
                            "backendAddressPool": {
                                "id": "[concat(resourceId('Microsoft.Network/loadBalancers', parameters('loadbalancerName')), '/backendAddressPools/loadBalancerBackEnd')]"
                            },
                            "probe": {
                                "id": "[concat(resourceId('Microsoft.Network/loadBalancers', parameters('loadbalancerName')), '/probes/webTrafficProbe')]"
                            },
                            "protocol": "Tcp",
                            "frontendPort": 80,
                            "backendPort": 80,
                            "idleTimeoutInMinutes": 15,
                            "loadDistribution": "SourceIP"
                        },
                        "name": "webTrafficRule"
                    },
                    {
                        "properties": {
                            "frontendIPConfiguration": {
                                "id": "[concat(resourceId('Microsoft.Network/loadBalancers', parameters('loadbalancerName')), '/frontendIpConfigurations/loadBalancerFrontEnd')]"
                            },
                            "backendAddressPool": {
                                "id": "[concat(resourceId('Microsoft.Network/loadBalancers', parameters('loadbalancerName')), '/backendAddressPools/loadBalancerBackEnd')]"
                            },
                            "probe": {
                                "id": "[concat(resourceId('Microsoft.Network/loadBalancers', parameters('loadbalancerName')), '/probes/webTrafficProbeHttps')]"
                            },
                            "protocol": "Tcp",
                            "frontendPort": 443,
                            "backendPort": 443,
                            "idleTimeoutInMinutes": 15,
                            "loadDistribution": "SourceIP"
                        },
                        "name": "webTrafficRuleHttps"
                    }
                ],
                "probes": [
                    {
                        "properties": {
                            "protocol": "Tcp",
                            "port": 80,
                            "intervalInSeconds": 15,
                            "numberOfProbes": 2
                        },
                        "name": "webTrafficProbe"
                    },
                    {
                        "properties": {
                            "protocol": "Tcp",
                            "port": 443,
                            "intervalInSeconds": 15,
                            "numberOfProbes": 2
                        },
                        "name": "webTrafficProbeHttps"
                    }
                ]
            }
        },
              {
        "apiVersion": "2015-06-15",
        "type": "Microsoft.Network/networkInterfaces",
        "name": "[concat(parameters('vmName'),'-nic' )]",
        "location": "[resourceGroup().location]",
        "tags": {
          "displayName": "NetworkInterface",
          "Environment": "[parameters('environment')]",
          "BuildDate": "[parameters('buildDate')]",
          "BuildBy": "[parameters('buildBy')]"
        },
        "dependsOn": [ ],
        "properties": {
          "ipConfigurations": [
            {
              "name": "ipconfig1",
              "properties": {
                "privateIPAllocationMethod": "Dynamic",
                "subnet": {
                  "id": "[parameters('subnetRef')]"
                }
              }
            }
          ]
        }
      }
    ],
    "outputs": {
        "appsloadBalancerBackendAddressPoolRef": {
            "type": "string",
            "value": "[concat(resourceId('Microsoft.Network/loadBalancers', parameters('loadbalancerName')), '/backendAddressPools/loadBalancerBackEnd')]"
        }
    }
}
